LICENSE
MANIFEST.in
README.md
setup.py
line/__init__.py
line/authentications.py
line/core.py
line/exceptions.py
line/logger.py
line_web.egg-info/PKG-INFO
line_web.egg-info/SOURCES.txt
line_web.egg-info/dependency_links.txt
line_web.egg-info/requires.txt
line_web.egg-info/top_level.txt